skill_communication/LICENSE.md
skill_communication/README.md
skill_communication/__init__.py
skill_communication/skill.json
skill_communication/version.py
skill_communication/locale/en-us/dialog/cant_call.dialog
skill_communication/locale/en-us/dialog/cant_send.dialog
skill_communication/locale/en-us/dialog/one_moment.dialog
skill_communication/locale/en-us/vocab/call.intent
skill_communication/locale/en-us/vocab/draft.voc
skill_communication/locale/en-us/vocab/message.voc
skill_communication/locale/en-us/vocab/neon.voc
skill_communication/locale/uk-ua/dialog/cant_call.dialog
skill_communication/locale/uk-ua/dialog/cant_send.dialog
skill_communication/locale/uk-ua/dialog/one_moment.dialog
skill_communication/locale/uk-ua/vocab/call.intent
skill_communication/locale/uk-ua/vocab/draft.voc
skill_communication/locale/uk-ua/vocab/message.voc
skill_communication/locale/uk-ua/vocab/neon.voc
skill_communication/neon_skill_communication.egg-info/PKG-INFO
skill_communication/neon_skill_communication.egg-info/SOURCES.txt
skill_communication/neon_skill_communication.egg-info/dependency_links.txt
skill_communication/neon_skill_communication.egg-info/entry_points.txt
skill_communication/neon_skill_communication.egg-info/requires.txt
skill_communication/neon_skill_communication.egg-info/top_level.txt
skill_communication/test/test_skill.py
neon_skill_communication-0.2.0.dist-info/LICENSE.md
neon_skill_communication-0.2.0.dist-info/METADATA
neon_skill_communication-0.2.0.dist-info/WHEEL
neon_skill_communication-0.2.0.dist-info/entry_points.txt
neon_skill_communication-0.2.0.dist-info/top_level.txt
neon_skill_communication-0.2.0.dist-info/RECORD
